pyopticon/__init__.py
pyopticon/dashboard.py
pyopticon/demo_dashboard.py
pyopticon/generic_widget.py
pyopticon/minimal_widget.py
pyopticon/socket_client.py
pyopticon/_system/__init__.py
pyopticon/_system/_automation_widget.py
pyopticon/_system/_data_logging_widget.py
pyopticon/_system/_serial_widget.py
pyopticon/_system/_show_hide_widget.py
pyopticon/_system/_socket_widget.py
pyopticon/built_in_widgets/__init__.py
pyopticon/built_in_widgets/spiciness_widget.py
pyopticon/built_in_widgets/title_widget.py
pyopticon/majumdar_lab_widgets/__init__.py
pyopticon/majumdar_lab_widgets/aalborg_dpc_widget.py
pyopticon/majumdar_lab_widgets/control_iot_relay_v1.ino
pyopticon/majumdar_lab_widgets/iot_relay_widget.py
pyopticon/majumdar_lab_widgets/mks_ftir_widget.py
pyopticon/majumdar_lab_widgets/mks_mfc_widget.py
pyopticon/majumdar_lab_widgets/omega_usb_utc_widget.py
pyopticon/majumdar_lab_widgets/picarro_crd_widget.py
pyopticon/majumdar_lab_widgets/sri_gc_fid_widget.py
pyopticon/majumdar_lab_widgets/thorlabs_light_meter_widget.py
pyopticon/majumdar_lab_widgets/valco_2_way_valve_widget.py
pyopticon/majumdar_lab_widgets/thorlabs/PM100D_64.dll
pyopticon/majumdar_lab_widgets/thorlabs/TLPM.py
pyopticon/majumdar_lab_widgets/thorlabs/TLPM_64.dll
pyopticon/majumdar_lab_widgets/thorlabs/desktop.ini
pyopticon/utilities/__init__.py
pyopticon/utilities/gmail_helper.py
pyopticon/utilities/serial_port_scanner.py
pyopticon-0.2.1.dist-info/METADATA
pyopticon-0.2.1.dist-info/WHEEL
pyopticon-0.2.1.dist-info/licenses/LICENSE
pyopticon-0.2.1.dist-info/RECORD
