Metadata-Version: 2.4
Name: pyopticon
Version: 0.2.1
Summary: A laboratory GUI, data acquisition, and automation package.
Project-URL: Homepage, https://github.com/richardsrandall/pyopticon
Author-email: Richard Randall <rrandall@stanford.edu>
License-File: LICENSE
Classifier: Operating System :: OS Independent
Classifier: Programming Language :: Python :: 3
Requires-Python: >=3.7
